{
  "data": [
    {
      "_id": "5d99beb677015a5c2c14542e",
      "amount": 10,
      "type": "outcome",
      "name": {
        "first": "Jordan",
        "last": "Bauer"
      },
      "company": "SNORUS",
      "email": "jordan.bauer@snorus.net",
      "phone": "+1 (901) 404-2928",
      "address": "712 Bills Place, Cochranville, Florida, 6951"
    },
    {
      "_id": "5d99beb69a6aac64be820dbe",
      "amount": 15,
      "type": "outcome",
      "name": {
        "first": "Francis",
        "last": "Owens"
      },
      "company": "EXOPLODE",
      "email": "francis.owens@exoplode.us",
      "phone": "+1 (954) 566-2476",
      "address": "457 Stockholm Street, Montura, Pennsylvania, 7855"
    },
    {
      "_id": "5d99beb635dd82195040195b",
      "amount": 7,
      "type": "outcome",
      "name": {
        "first": "Bass",
        "last": "Church"
      },
      "company": "ACCRUEX",
      "email": "bass.church@accruex.com",
      "phone": "+1 (881) 403-2661",
      "address": "786 Ira Court, Abiquiu, Kentucky, 1055"
    },
    {
      "_id": "5d99beb6283bac04b3763000",
      "amount": 6,
      "type": "outcome",
      "name": {
        "first": "Mabel",
        "last": "Holt"
      },
      "company": "MALATHION",
      "email": "mabel.holt@malathion.io",
      "phone": "+1 (951) 520-3392",
      "address": "890 Alice Court, Bath, New Hampshire, 6400"
    },
    {
      "_id": "5d99beb6207f35413c9b629b",
      "amount": 7,
      "type": "loan",
      "name": {
        "first": "Lambert",
        "last": "Higgins"
      },
      "company": "GEEKOLOGY",
      "email": "lambert.higgins@geekology.name",
      "phone": "+1 (957) 573-3207",
      "address": "513 Schroeders Avenue, Moquino, Connecticut, 6353"
    },
    {
      "_id": "5d99beb6f6db754cee0835a0",
      "amount": 5,
      "type": "income",
      "name": {
        "first": "Jeanie",
        "last": "Wiley"
      },
      "company": "CORECOM",
      "email": "jeanie.wiley@corecom.tv",
      "phone": "+1 (931) 432-2272",
      "address": "196 Highland Boulevard, Wildwood, Georgia, 8732"
    },
    {
      "_id": "5d99beb6c0c5d1e73c8bb5a2",
      "amount": 2,
      "type": "income",
      "name": {
        "first": "Lynn",
        "last": "Summers"
      },
      "company": "BLUEGRAIN",
      "email": "lynn.summers@bluegrain.biz",
      "phone": "+1 (877) 578-3987",
      "address": "999 Ellery Street, Hartsville/Hartley, Tennessee, 8475"
    },
    {
      "_id": "5d99beb69aec11b778e276c9",
      "amount": 15,
      "type": "investment",
      "name": {
        "first": "Roseann",
        "last": "Lowe"
      },
      "company": "NORALI",
      "email": "roseann.lowe@norali.org",
      "phone": "+1 (969) 433-3912",
      "address": "209 Saratoga Avenue, Riegelwood, Northern Mariana Islands, 3804"
    },
    {
      "_id": "5d99beb61851f0fadfe6bca0",
      "amount": 2,
      "type": "loan",
      "name": {
        "first": "Dianna",
        "last": "Underwood"
      },
      "company": "GEOLOGIX",
      "email": "dianna.underwood@geologix.me",
      "phone": "+1 (831) 506-2281",
      "address": "379 Polar Street, Derwood, Michigan, 8219"
    },
    {
      "_id": "5d99beb61894e3a0d8a8aaeb",
      "amount": 11,
      "type": "investment",
      "name": {
        "first": "Misty",
        "last": "Wells"
      },
      "company": "ZILCH",
      "email": "misty.wells@zilch.info",
      "phone": "+1 (803) 453-3224",
      "address": "473 Rochester Avenue, Kraemer, Illinois, 140"
    },
    {
      "_id": "5d99beb6b15536f75b46a608",
      "amount": 27,
      "type": "investment",
      "name": {
        "first": "Tammie",
        "last": "Cotton"
      },
      "company": "GENMOM",
      "email": "tammie.cotton@genmom.co.uk",
      "phone": "+1 (891) 471-2924",
      "address": "599 Juliana Place, Alafaya, Maryland, 917"
    },
    {
      "_id": "5d99beb62fc237aa62133abc",
      "amount": 4,
      "type": "income",
      "name": {
        "first": "Rasmussen",
        "last": "Paul"
      },
      "company": "SUPPORTAL",
      "email": "rasmussen.paul@supportal.biz",
      "phone": "+1 (829) 473-3553",
      "address": "164 Cedar Street, Basye, District Of Columbia, 5164"
    },
    {
      "_id": "5d99beb6e0f76b46c0f5ce21",
      "amount": 3,
      "type": "outcome",
      "name": {
        "first": "Allie",
        "last": "Solomon"
      },
      "company": "TOYLETRY",
      "email": "allie.solomon@toyletry.net",
      "phone": "+1 (835) 596-3561",
      "address": "335 Noll Street, Ernstville, New York, 5938"
    },
    {
      "_id": "5d99beb67ba49c6e156b8999",
      "amount": 6,
      "type": "investment",
      "name": {
        "first": "Hammond",
        "last": "Stanton"
      },
      "company": "XTH",
      "email": "hammond.stanton@xth.us",
      "phone": "+1 (967) 413-2650",
      "address": "468 Clifton Place, Harold, Puerto Rico, 2501"
    },
    {
      "_id": "5d99beb6b13450897a61c8b0",
      "amount": 8,
      "type": "loan",
      "name": {
        "first": "Scott",
        "last": "Petty"
      },
      "company": "ZOINAGE",
      "email": "scott.petty@zoinage.com",
      "phone": "+1 (913) 425-3420",
      "address": "475 Herkimer Street, Barstow, Utah, 9466"
    },
    {
      "_id": "5d99beb6f9f4e1748d85a971",
      "amount": 8,
      "type": "outcome",
      "name": {
        "first": "Alexander",
        "last": "Harrell"
      },
      "company": "RONELON",
      "email": "alexander.harrell@ronelon.io",
      "phone": "+1 (940) 577-2114",
      "address": "962 Falmouth Street, Loma, Iowa, 2743"
    },
    {
      "_id": "5d99beb600162e31cce6d255",
      "amount": 4,
      "type": "loan",
      "name": {
        "first": "Letitia",
        "last": "Combs"
      },
      "company": "PHOLIO",
      "email": "letitia.combs@pholio.name",
      "phone": "+1 (962) 515-2518",
      "address": "480 Tapscott Avenue, Remington, Arkansas, 4987"
    },
    {
      "_id": "5d99beb6f46990cdedd7a054",
      "amount": 5,
      "type": "loan",
      "name": {
        "first": "Myers",
        "last": "Russell"
      },
      "company": "IDEGO",
      "email": "myers.russell@idego.tv",
      "phone": "+1 (923) 524-3492",
      "address": "912 Veronica Place, Sugartown, Alabama, 1510"
    },
    {
      "_id": "5d99beb68066435dd603b971",
      "amount": 27,
      "type": "outcome",
      "name": {
        "first": "Daphne",
        "last": "Pearson"
      },
      "company": "ZYTREK",
      "email": "daphne.pearson@zytrek.biz",
      "phone": "+1 (887) 565-2927",
      "address": "786 Elliott Walk, Collins, California, 7185"
    },
    {
      "_id": "5d99beb6481acdc4f1f2dbcd",
      "amount": 22,
      "type": "loan",
      "name": {
        "first": "Dillon",
        "last": "Hull"
      },
      "company": "CENTURIA",
      "email": "dillon.hull@centuria.org",
      "phone": "+1 (882) 473-3051",
      "address": "915 Dekoven Court, Tyhee, Indiana, 7029"
    },
    {
      "_id": "5d99beb66abe615580c7868c",
      "amount": 18,
      "type": "income",
      "name": {
        "first": "Reese",
        "last": "Hunt"
      },
      "company": "KEENGEN",
      "email": "reese.hunt@keengen.me",
      "phone": "+1 (983) 503-2309",
      "address": "280 Delevan Street, Tyro, Nebraska, 3995"
    },
    {
      "_id": "5d99beb6cf9df8720ce4e771",
      "amount": 8,
      "type": "investment",
      "name": {
        "first": "Howard",
        "last": "Hodge"
      },
      "company": "KIOSK",
      "email": "howard.hodge@kiosk.info",
      "phone": "+1 (937) 538-3339",
      "address": "350 Schenectady Avenue, Osmond, North Carolina, 6893"
    },
    {
      "_id": "5d99beb6022f6189a1f23970",
      "amount": 10,
      "type": "loan",
      "name": {
        "first": "Kathleen",
        "last": "Patel"
      },
      "company": "ACCUFARM",
      "email": "kathleen.patel@accufarm.co.uk",
      "phone": "+1 (988) 567-3882",
      "address": "801 Albany Avenue, Greenbackville, Delaware, 8396"
    },
    {
      "_id": "5d99beb6230c62aa8243ff80",
      "amount": 11,
      "type": "outcome",
      "name": {
        "first": "Amparo",
        "last": "Horne"
      },
      "company": "MARQET",
      "email": "amparo.horne@marqet.biz",
      "phone": "+1 (958) 519-3437",
      "address": "584 Colonial Court, Waterview, Oregon, 8213"
    },
    {
      "_id": "5d99beb6f7f32d24da875f1b",
      "amount": 12,
      "type": "investment",
      "name": {
        "first": "Acevedo",
        "last": "Finley"
      },
      "company": "DANCITY",
      "email": "acevedo.finley@dancity.net",
      "phone": "+1 (955) 598-3527",
      "address": "185 Amboy Street, Elliston, Virgin Islands, 374"
    },
    {
      "_id": "5d99beb68b54b0c3a0ef3470",
      "amount": 3,
      "type": "income",
      "name": {
        "first": "Moore",
        "last": "Strong"
      },
      "company": "TELEQUIET",
      "email": "moore.strong@telequiet.us",
      "phone": "+1 (809) 406-3732",
      "address": "542 Will Place, Hampstead, Montana, 6733"
    },
    {
      "_id": "5d99beb6b7490a9aacc00b1a",
      "amount": 4,
      "type": "investment",
      "name": {
        "first": "Ina",
        "last": "Becker"
      },
      "company": "QUOTEZART",
      "email": "ina.becker@quotezart.com",
      "phone": "+1 (955) 491-3087",
      "address": "699 Miller Place, Glidden, Idaho, 6159"
    },
    {
      "_id": "5d99beb64e9dfcb53acd8626",
      "amount": 5,
      "type": "outcome",
      "name": {
        "first": "Dorsey",
        "last": "Juarez"
      },
      "company": "ENERSAVE",
      "email": "dorsey.juarez@enersave.io",
      "phone": "+1 (937) 403-2109",
      "address": "427 Rock Street, Joppa, New Jersey, 9046"
    },
    {
      "_id": "5d99beb6f53bb9cc0b870839",
      "amount": 12,
      "type": "loan",
      "name": {
        "first": "Wolfe",
        "last": "Michael"
      },
      "company": "ISOLOGIA",
      "email": "wolfe.michael@isologia.name",
      "phone": "+1 (928) 559-2490",
      "address": "612 Varick Street, Charco, West Virginia, 8585"
    },
    {
      "_id": "5d99beb626d3124fa91e7429",
      "amount": 16,
      "type": "outcome",
      "name": {
        "first": "Manning",
        "last": "Preston"
      },
      "company": "GENMY",
      "email": "manning.preston@genmy.tv",
      "phone": "+1 (897) 497-3105",
      "address": "161 Hubbard Street, Coaldale, Wyoming, 617"
    },
    {
      "_id": "5d99beb664a4e4c72591f9a3",
      "amount": 15,
      "type": "income",
      "name": {
        "first": "Tucker",
        "last": "Bender"
      },
      "company": "SUPREMIA",
      "email": "tucker.bender@supremia.biz",
      "phone": "+1 (934) 461-2588",
      "address": "844 Metropolitan Avenue, Brule, Colorado, 3619"
    },
    {
      "_id": "5d99beb66b24688a0de700a0",
      "amount": 10,
      "type": "outcome",
      "name": {
        "first": "Skinner",
        "last": "Mcfarland"
      },
      "company": "ZBOO",
      "email": "skinner.mcfarland@zboo.org",
      "phone": "+1 (965) 468-3953",
      "address": "513 Clarkson Avenue, Crawfordsville, Palau, 2489"
    },
    {
      "_id": "5d99beb6c0dba22f51f3adc2",
      "amount": 3,
      "type": "investment",
      "name": {
        "first": "Farrell",
        "last": "Campbell"
      },
      "company": "HALAP",
      "email": "farrell.campbell@halap.me",
      "phone": "+1 (803) 588-2940",
      "address": "481 Suydam Place, Machias, South Dakota, 1384"
    },
    {
      "_id": "5d99beb6d3647cf8b14c9409",
      "amount": 2,
      "type": "income",
      "name": {
        "first": "Cathy",
        "last": "Oneil"
      },
      "company": "ACUSAGE",
      "email": "cathy.oneil@acusage.info",
      "phone": "+1 (924) 587-3879",
      "address": "663 Dahill Road, Crucible, Oklahoma, 4041"
    },
    {
      "_id": "5d99beb698d1fbade2a863a3",
      "amount": 9,
      "type": "outcome",
      "name": {
        "first": "Lindsey",
        "last": "Gates"
      },
      "company": "HOTCAKES",
      "email": "lindsey.gates@hotcakes.co.uk",
      "phone": "+1 (912) 502-2920",
      "address": "958 Crescent Street, Coyote, Vermont, 2958"
    },
    {
      "_id": "5d99beb633f3e5c3e8378aa7",
      "amount": 9,
      "type": "outcome",
      "name": {
        "first": "Key",
        "last": "Armstrong"
      },
      "company": "VISUALIX",
      "email": "key.armstrong@visualix.biz",
      "phone": "+1 (845) 531-2978",
      "address": "933 Woodpoint Road, Fontanelle, New Mexico, 7487"
    },
    {
      "_id": "5d99beb6af9bf2e627e8f6ad",
      "amount": 7,
      "type": "outcome",
      "name": {
        "first": "Mueller",
        "last": "Woods"
      },
      "company": "SENSATE",
      "email": "mueller.woods@sensate.net",
      "phone": "+1 (853) 514-2094",
      "address": "804 Kermit Place, Cetronia, Maine, 3848"
    },
    {
      "_id": "5d99beb6967feb03ef03b2e9",
      "amount": 30,
      "type": "investment",
      "name": {
        "first": "Stacey",
        "last": "Aguilar"
      },
      "company": "ENAUT",
      "email": "stacey.aguilar@enaut.us",
      "phone": "+1 (919) 573-2912",
      "address": "237 Concord Street, Bannock, Mississippi, 2727"
    },
    {
      "_id": "5d99beb6069071371bb4fe57",
      "amount": 25,
      "type": "investment",
      "name": {
        "first": "Fitzpatrick",
        "last": "Martinez"
      },
      "company": "HINWAY",
      "email": "fitzpatrick.martinez@hinway.com",
      "phone": "+1 (868) 569-2829",
      "address": "856 Willoughby Avenue, Draper, Washington, 4905"
    },
    {
      "_id": "5d99beb645e90e295a14abaf",
      "amount": 27,
      "type": "investment",
      "name": {
        "first": "Sanchez",
        "last": "Hooper"
      },
      "company": "REVERSUS",
      "email": "sanchez.hooper@reversus.io",
      "phone": "+1 (934) 445-2142",
      "address": "489 Roebling Street, Gorst, Guam, 5212"
    },
    {
      "_id": "5d99beb65b3f217fd4c9fe32",
      "amount": 14,
      "type": "loan",
      "name": {
        "first": "Christian",
        "last": "Henry"
      },
      "company": "QUALITEX",
      "email": "christian.henry@qualitex.name",
      "phone": "+1 (871) 451-2636",
      "address": "515 Baycliff Terrace, Englevale, Massachusetts, 2526"
    },
    {
      "_id": "5d99beb690336c6b9a82eb4a",
      "amount": 15,
      "type": "outcome",
      "name": {
        "first": "Jodie",
        "last": "Guerrero"
      },
      "company": "ZENTIME",
      "email": "jodie.guerrero@zentime.tv",
      "phone": "+1 (849) 571-3318",
      "address": "995 Tampa Court, Bloomington, Minnesota, 4717"
    },
    {
      "_id": "5d99beb6c3b33f427845205d",
      "amount": 16,
      "type": "outcome",
      "name": {
        "first": "Conley",
        "last": "Monroe"
      },
      "company": "CANOPOLY",
      "email": "conley.monroe@canopoly.biz",
      "phone": "+1 (981) 584-2075",
      "address": "439 Paerdegat Avenue, Gouglersville, Hawaii, 3452"
    },
    {
      "_id": "5d99beb6121ba61ba9c779bc",
      "amount": 19,
      "type": "loan",
      "name": {
        "first": "Janell",
        "last": "Banks"
      },
      "company": "ZORK",
      "email": "janell.banks@zork.org",
      "phone": "+1 (957) 525-3157",
      "address": "706 Kimball Street, Brutus, Marshall Islands, 3668"
    },
    {
      "_id": "5d99beb6e7771bb8cff666d6",
      "amount": 21,
      "type": "outcome",
      "name": {
        "first": "Ward",
        "last": "Castro"
      },
      "company": "SIGNIDYNE",
      "email": "ward.castro@signidyne.me",
      "phone": "+1 (881) 450-3092",
      "address": "346 Atkins Avenue, Gloucester, Federated States Of Micronesia, 2540"
    },
    {
      "_id": "5d99beb6086149feeefc2e66",
      "amount": 21,
      "type": "loan",
      "name": {
        "first": "Hogan",
        "last": "Walter"
      },
      "company": "BARKARAMA",
      "email": "hogan.walter@barkarama.info",
      "phone": "+1 (815) 574-2671",
      "address": "857 Indiana Place, Esmont, Texas, 8818"
    },
    {
      "_id": "5d99beb6ff11eacb34de4f10",
      "amount": 20,
      "type": "loan",
      "name": {
        "first": "Inez",
        "last": "Zamora"
      },
      "company": "ESSENSIA",
      "email": "inez.zamora@essensia.co.uk",
      "phone": "+1 (894) 557-2393",
      "address": "465 Tompkins Place, Caron, Wisconsin, 5950"
    },
    {
      "_id": "5d99beb60be55eb1da68c4ba",
      "amount": 9,
      "type": "loan",
      "name": {
        "first": "Bridges",
        "last": "Patton"
      },
      "company": "SONGBIRD",
      "email": "bridges.patton@songbird.biz",
      "phone": "+1 (929) 410-2526",
      "address": "137 Apollo Street, Balm, Arizona, 1965"
    },
    {
      "_id": "5d99beb64337005cefde4626",
      "amount": 9,
      "type": "loan",
      "name": {
        "first": "Grimes",
        "last": "Jenkins"
      },
      "company": "GINKLE",
      "email": "grimes.jenkins@ginkle.net",
      "phone": "+1 (916) 426-2443",
      "address": "397 Ashland Place, Cedarville, Kansas, 8820"
    },
    {
      "_id": "5d99beb6f7e4e652c75868a8",
      "amount": 7,
      "type": "investment",
      "name": {
        "first": "Shepherd",
        "last": "Durham"
      },
      "company": "ZEAM",
      "email": "shepherd.durham@zeam.us",
      "phone": "+1 (970) 570-2377",
      "address": "826 Union Avenue, Walker, Rhode Island, 9180"
    },
    {
      "_id": "5d99beb63c892055952c1908",
      "amount": 3,
      "type": "investment",
      "name": {
        "first": "Morris",
        "last": "Stephens"
      },
      "company": "AQUACINE",
      "email": "morris.stephens@aquacine.com",
      "phone": "+1 (854) 409-3865",
      "address": "183 Tehama Street, Spokane, Nevada, 2375"
    },
    {
      "_id": "5d99beb6c614fe4c8ca3c023",
      "amount": 3,
      "type": "investment",
      "name": {
        "first": "Josie",
        "last": "House"
      },
      "company": "ISOSURE",
      "email": "josie.house@isosure.io",
      "phone": "+1 (901) 547-2615",
      "address": "659 Hill Street, Rowe, Missouri, 8918"
    },
    {
      "_id": "5d99beb6558891537809623e",
      "amount": 5,
      "type": "loan",
      "name": {
        "first": "Hall",
        "last": "Brewer"
      },
      "company": "UBERLUX",
      "email": "hall.brewer@uberlux.name",
      "phone": "+1 (954) 436-3000",
      "address": "335 Cumberland Walk, Loveland, North Dakota, 853"
    },
    {
      "_id": "5d99beb6a5060fbac46cc79d",
      "amount": 6,
      "type": "investment",
      "name": {
        "first": "Perkins",
        "last": "Watkins"
      },
      "company": "RUBADUB",
      "email": "perkins.watkins@rubadub.tv",
      "phone": "+1 (822) 587-3479",
      "address": "240 Independence Avenue, Wanamie, Alaska, 3833"
    },
    {
      "_id": "5d99beb68533edf2fdc241bb",
      "amount": 7,
      "type": "investment",
      "name": {
        "first": "Bender",
        "last": "Rivas"
      },
      "company": "UNIA",
      "email": "bender.rivas@unia.biz",
      "phone": "+1 (826) 448-3886",
      "address": "255 McDonald Avenue, Soudan, Louisiana, 6344"
    },
    {
      "_id": "5d99beb6ba779217e965a21c",
      "amount": 3,
      "type": "outcome",
      "name": {
        "first": "Boone",
        "last": "Butler"
      },
      "company": "OPTICOM",
      "email": "boone.butler@opticom.org",
      "phone": "+1 (943) 451-3074",
      "address": "895 Whitney Avenue, Curtice, Ohio, 150"
    },
    {
      "_id": "5d99beb6ffddf4af466b7a06",
      "amount": 5,
      "type": "income",
      "name": {
        "first": "Cathleen",
        "last": "Brown"
      },
      "company": "FIBEROX",
      "email": "cathleen.brown@fiberox.me",
      "phone": "+1 (809) 550-3045",
      "address": "864 Nautilus Avenue, Tuttle, Virginia, 1619"
    },
    {
      "_id": "5d99beb6d927af5635543e87",
      "amount": 6,
      "type": "investment",
      "name": {
        "first": "Marcia",
        "last": "Haley"
      },
      "company": "SENMEI",
      "email": "marcia.haley@senmei.info",
      "phone": "+1 (844) 436-3094",
      "address": "388 Debevoise Avenue, Denio, American Samoa, 4603"
    },
    {
      "_id": "5d99beb6b0699f34547ef9cd",
      "amount": 8,
      "type": "outcome",
      "name": {
        "first": "Claire",
        "last": "Curtis"
      },
      "company": "EXOSIS",
      "email": "claire.curtis@exosis.co.uk",
      "phone": "+1 (960) 540-2403",
      "address": "427 Covert Street, Fingerville, Florida, 3375"
    },
    {
      "_id": "5d99beb61eac41d3bcaeea76",
      "amount": 1,
      "type": "income",
      "name": {
        "first": "Gardner",
        "last": "Burch"
      },
      "company": "MARTGO",
      "email": "gardner.burch@martgo.biz",
      "phone": "+1 (966) 574-3591",
      "address": "513 Lois Avenue, Sanders, Pennsylvania, 8293"
    },
    {
      "_id": "5d99beb6ef3b7cd3990499d8",
      "amount": 9,
      "type": "outcome",
      "name": {
        "first": "Mercer",
        "last": "Sexton"
      },
      "company": "PUSHCART",
      "email": "mercer.sexton@pushcart.net",
      "phone": "+1 (999) 417-2060",
      "address": "225 Vandervoort Place, Kerby, Kentucky, 9591"
    },
    {
      "_id": "5d99beb6815f3f77883aaf66",
      "amount": 15,
      "type": "investment",
      "name": {
        "first": "Rebecca",
        "last": "Odonnell"
      },
      "company": "IMKAN",
      "email": "rebecca.odonnell@imkan.us",
      "phone": "+1 (962) 484-3520",
      "address": "895 Troy Avenue, Watchtower, New Hampshire, 9063"
    },
    {
      "_id": "5d99beb6adcc0c81c5e63963",
      "amount": 16,
      "type": "outcome",
      "name": {
        "first": "Church",
        "last": "Vance"
      },
      "company": "EARBANG",
      "email": "church.vance@earbang.com",
      "phone": "+1 (815) 531-3967",
      "address": "600 Adams Street, Dola, Connecticut, 9089"
    },
    {
      "_id": "5d99beb685d74a082da6bc67",
      "amount": 17,
      "type": "investment",
      "name": {
        "first": "Jocelyn",
        "last": "Henderson"
      },
      "company": "MATRIXITY",
      "email": "jocelyn.henderson@matrixity.io",
      "phone": "+1 (801) 423-2390",
      "address": "781 Fairview Place, Eagleville, Georgia, 2656"
    },
    {
      "_id": "5d99beb688c61720ca3ce583",
      "amount": 18,
      "type": "investment",
      "name": {
        "first": "Virginia",
        "last": "Vega"
      },
      "company": "MITROC",
      "email": "virginia.vega@mitroc.name",
      "phone": "+1 (981) 544-3928",
      "address": "657 Bedell Lane, Springhill, Tennessee, 5426"
    },
    {
      "_id": "5d99beb6639c96a75559eeac",
      "amount": 11,
      "type": "investment",
      "name": {
        "first": "Odonnell",
        "last": "Lewis"
      },
      "company": "GEOFORMA",
      "email": "odonnell.lewis@geoforma.tv",
      "phone": "+1 (996) 457-3721",
      "address": "898 Montauk Avenue, Sehili, Northern Mariana Islands, 752"
    },
    {
      "_id": "5d99beb67a6153f9b5df016e",
      "amount": 9,
      "type": "income",
      "name": {
        "first": "Tia",
        "last": "Best"
      },
      "company": "KINETICUT",
      "email": "tia.best@kineticut.biz",
      "phone": "+1 (903) 494-3935",
      "address": "760 Wallabout Street, Neahkahnie, Michigan, 5540"
    },
    {
      "_id": "5d99beb6fb959e811bd36cb4",
      "amount": 7,
      "type": "loan",
      "name": {
        "first": "Duran",
        "last": "Russo"
      },
      "company": "TROPOLIS",
      "email": "duran.russo@tropolis.org",
      "phone": "+1 (855) 478-2256",
      "address": "967 Horace Court, Starks, Illinois, 888"
    },
    {
      "_id": "5d99beb64ffa3eefb4f844ae",
      "amount": 6,
      "type": "outcome",
      "name": {
        "first": "Margo",
        "last": "Gill"
      },
      "company": "TASMANIA",
      "email": "margo.gill@tasmania.me",
      "phone": "+1 (815) 567-2478",
      "address": "755 Haring Street, Rote, Maryland, 773"
    },
    {
      "_id": "5d99beb626a11674d75bba44",
      "amount": 25,
      "type": "income",
      "name": {
        "first": "Lyons",
        "last": "Hobbs"
      },
      "company": "MOMENTIA",
      "email": "lyons.hobbs@momentia.info",
      "phone": "+1 (992) 545-2079",
      "address": "468 Rogers Avenue, Troy, District Of Columbia, 5550"
    },
    {
      "_id": "5d99beb6b6d969195fff486f",
      "amount": 31,
      "type": "investment",
      "name": {
        "first": "Gonzales",
        "last": "Horn"
      },
      "company": "TELPOD",
      "email": "gonzales.horn@telpod.co.uk",
      "phone": "+1 (948) 401-2653",
      "address": "976 Jamison Lane, Morriston, New York, 2635"
    },
    {
      "_id": "5d99beb6e28b54e75b93127f",
      "amount": 5,
      "type": "loan",
      "name": {
        "first": "Larsen",
        "last": "Merritt"
      },
      "company": "CIRCUM",
      "email": "larsen.merritt@circum.biz",
      "phone": "+1 (801) 587-3681",
      "address": "544 Ditmas Avenue, Stockdale, Puerto Rico, 5202"
    },
    {
      "_id": "5d99beb62ddbe863c0e68462",
      "amount": 5,
      "type": "outcome",
      "name": {
        "first": "Bradshaw",
        "last": "Browning"
      },
      "company": "MAGNEMO",
      "email": "bradshaw.browning@magnemo.net",
      "phone": "+1 (881) 483-2401",
      "address": "179 Centre Street, Worcester, Utah, 4299"
    },
    {
      "_id": "5d99beb6064d6307872d67d3",
      "amount": 5,
      "type": "outcome",
      "name": {
        "first": "Leta",
        "last": "Hayden"
      },
      "company": "UNIWORLD",
      "email": "leta.hayden@uniworld.us",
      "phone": "+1 (842) 436-2136",
      "address": "975 Irwin Street, Leming, Iowa, 4510"
    },
    {
      "_id": "5d99beb6410994433c7d1eba",
      "amount": 6,
      "type": "investment",
      "name": {
        "first": "Baxter",
        "last": "Craft"
      },
      "company": "BALUBA",
      "email": "baxter.craft@baluba.com",
      "phone": "+1 (858) 400-3810",
      "address": "695 Quincy Street, Retsof, Arkansas, 2277"
    },
    {
      "_id": "5d99beb65bf1a846313590f0",
      "amount": 15,
      "type": "investment",
      "name": {
        "first": "Chen",
        "last": "Riley"
      },
      "company": "ECSTASIA",
      "email": "chen.riley@ecstasia.io",
      "phone": "+1 (944) 487-3236",
      "address": "897 Devoe Street, Conestoga, Alabama, 3810"
    },
    {
      "_id": "5d99beb6fc1c67e102aee9e7",
      "amount": 15,
      "type": "loan",
      "name": {
        "first": "Mcfarland",
        "last": "Clayton"
      },
      "company": "ZENCO",
      "email": "mcfarland.clayton@zenco.name",
      "phone": "+1 (803) 451-2232",
      "address": "545 Dumont Avenue, Woodburn, California, 1170"
    },
    {
      "_id": "5d99beb63a32d412427672da",
      "amount": 15,
      "type": "outcome",
      "name": {
        "first": "Hernandez",
        "last": "Lee"
      },
      "company": "NURALI",
      "email": "hernandez.lee@nurali.tv",
      "phone": "+1 (819) 421-3593",
      "address": "687 Luquer Street, Cade, Indiana, 8731"
    },
    {
      "_id": "5d99beb61f78f116aafaad7b",
      "amount": 14,
      "type": "income",
      "name": {
        "first": "Katina",
        "last": "Solis"
      },
      "company": "SLAMBDA",
      "email": "katina.solis@slambda.biz",
      "phone": "+1 (945) 416-3177",
      "address": "583 Elton Street, Lund, Nebraska, 9403"
    },
    {
      "_id": "5d99beb6abc50cae2376910a",
      "amount": 13,
      "type": "loan",
      "name": {
        "first": "Tanya",
        "last": "Hewitt"
      },
      "company": "ZILLIDIUM",
      "email": "tanya.hewitt@zillidium.org",
      "phone": "+1 (885) 544-2633",
      "address": "197 Tillary Street, Nash, North Carolina, 9575"
    },
    {
      "_id": "5d99beb6a6c3c2ca5dcb855c",
      "amount": 14,
      "type": "loan",
      "name": {
        "first": "Tillman",
        "last": "Buchanan"
      },
      "company": "BOILICON",
      "email": "tillman.buchanan@boilicon.me",
      "phone": "+1 (997) 520-2562",
      "address": "741 Seigel Street, Whitestone, Delaware, 5588"
    },
    {
      "_id": "5d99beb695b05943e5dd78dd",
      "amount": 15,
      "type": "outcome",
      "name": {
        "first": "Maria",
        "last": "Hart"
      },
      "company": "PYRAMI",
      "email": "maria.hart@pyrami.info",
      "phone": "+1 (814) 400-2126",
      "address": "507 Royce Place, Makena, Oregon, 451"
    },
    {
      "_id": "5d99beb6608b27c39d17ce02",
      "amount": 16,
      "type": "loan",
      "name": {
        "first": "Sondra",
        "last": "Stuart"
      },
      "company": "CUBIX",
      "email": "sondra.stuart@cubix.co.uk",
      "phone": "+1 (924) 580-2223",
      "address": "845 Voorhies Avenue, Defiance, Virgin Islands, 2198"
    },
    {
      "_id": "5d99beb649dcf9042e8ebf3e",
      "amount": 18,
      "type": "income",
      "name": {
        "first": "Carpenter",
        "last": "Castillo"
      },
      "company": "PASTURIA",
      "email": "carpenter.castillo@pasturia.biz",
      "phone": "+1 (886) 528-2709",
      "address": "862 Colby Court, Hillsboro, Montana, 3192"
    },
    {
      "_id": "5d99beb6eff39a753c169f9c",
      "amount": 2,
      "type": "investment",
      "name": {
        "first": "Christina",
        "last": "Roman"
      },
      "company": "KINDALOO",
      "email": "christina.roman@kindaloo.net",
      "phone": "+1 (979) 517-2630",
      "address": "379 Evans Street, Bowden, Idaho, 5871"
    },
    {
      "_id": "5d99beb634e062b7a7bca29b",
      "amount": 3,
      "type": "income",
      "name": {
        "first": "Anna",
        "last": "Boyd"
      },
      "company": "DANCERITY",
      "email": "anna.boyd@dancerity.us",
      "phone": "+1 (887) 403-2364",
      "address": "183 Rockwell Place, Rosburg, New Jersey, 264"
    },
    {
      "_id": "5d99beb6fd10ed3634a91a16",
      "amount": 5,
      "type": "loan",
      "name": {
        "first": "Yolanda",
        "last": "Mcdonald"
      },
      "company": "OVATION",
      "email": "yolanda.mcdonald@ovation.com",
      "phone": "+1 (946) 502-2228",
      "address": "889 Herbert Street, Woodlands, West Virginia, 9435"
    },
    {
      "_id": "5d99beb67d581d81e0038c8e",
      "amount": 3,
      "type": "outcome",
      "name": {
        "first": "Kristi",
        "last": "Wilkins"
      },
      "company": "ZIALACTIC",
      "email": "kristi.wilkins@zialactic.io",
      "phone": "+1 (853) 441-3800",
      "address": "391 Dahlgreen Place, Twilight, Wyoming, 5130"
    },
    {
      "_id": "5d99beb654a34b0559076fe6",
      "amount": 33,
      "type": "investment",
      "name": {
        "first": "Stacie",
        "last": "Ortiz"
      },
      "company": "KONGLE",
      "email": "stacie.ortiz@kongle.name",
      "phone": "+1 (828) 468-3196",
      "address": "735 Bushwick Court, Ilchester, Colorado, 8597"
    },
    {
      "_id": "5d99beb6b28061f866d2c339",
      "amount": 4,
      "type": "outcome",
      "name": {
        "first": "Bonner",
        "last": "Carter"
      },
      "company": "IMAGINART",
      "email": "bonner.carter@imaginart.tv",
      "phone": "+1 (998) 548-2731",
      "address": "740 Harrison Place, Lacomb, Palau, 5392"
    },
    {
      "_id": "5d99beb65814fce715011141",
      "amount": 5,
      "type": "investment",
      "name": {
        "first": "Graciela",
        "last": "Deleon"
      },
      "company": "OVOLO",
      "email": "graciela.deleon@ovolo.biz",
      "phone": "+1 (841) 531-2309",
      "address": "975 McKibben Street, Nicholson, South Dakota, 5431"
    },
    {
      "_id": "5d99beb62061d5009c894004",
      "amount": 6,
      "type": "loan",
      "name": {
        "first": "Marsha",
        "last": "Chan"
      },
      "company": "ENORMO",
      "email": "marsha.chan@enormo.org",
      "phone": "+1 (829) 501-3906",
      "address": "765 Whitwell Place, Keyport, Oklahoma, 2647"
    },
    {
      "_id": "5d99beb66941cc9e3e358edd",
      "amount": 8,
      "type": "loan",
      "name": {
        "first": "Ladonna",
        "last": "Bentley"
      },
      "company": "NETPLODE",
      "email": "ladonna.bentley@netplode.me",
      "phone": "+1 (928) 512-3093",
      "address": "606 Cambridge Place, Harrison, Vermont, 8587"
    },
    {
      "_id": "5d99beb669a12f644f5139ee",
      "amount": 9,
      "type": "outcome",
      "name": {
        "first": "Alta",
        "last": "Thompson"
      },
      "company": "VOLAX",
      "email": "alta.thompson@volax.info",
      "phone": "+1 (889) 405-2732",
      "address": "357 Brighton Avenue, Dexter, New Mexico, 9046"
    },
    {
      "_id": "5d99beb6d97a1b21014e5ff1",
      "amount": 10,
      "type": "income",
      "name": {
        "first": "Ayala",
        "last": "Conrad"
      },
      "company": "EMTRAC",
      "email": "ayala.conrad@emtrac.co.uk",
      "phone": "+1 (850) 557-2894",
      "address": "168 Kane Street, Laurelton, Maine, 6367"
    },
    {
      "_id": "5d99beb6ccc8097475120981",
      "amount": 12,
      "type": "investment",
      "name": {
        "first": "Glenda",
        "last": "Lindsey"
      },
      "company": "ECLIPSENT",
      "email": "glenda.lindsey@eclipsent.biz",
      "phone": "+1 (887) 479-2196",
      "address": "383 Grove Street, Belvoir, Mississippi, 7175"
    },
    {
      "_id": "5d99beb645a511c0f6bce20b",
      "amount": 15,
      "type": "income",
      "name": {
        "first": "Rhodes",
        "last": "Lyons"
      },
      "company": "SYNKGEN",
      "email": "rhodes.lyons@synkgen.net",
      "phone": "+1 (943) 441-2257",
      "address": "602 Conselyea Street, Rockhill, Washington, 8676"
    },
    {
      "_id": "5d99beb6a22b596eaf635fd1",
      "amount": 2,
      "type": "loan",
      "name": {
        "first": "Bond",
        "last": "Talley"
      },
      "company": "DIGIGEN",
      "email": "bond.talley@digigen.us",
      "phone": "+1 (905) 498-2315",
      "address": "566 Central Avenue, Ebro, Guam, 8891"
    },
    {
      "_id": "5d99beb65daa71ef83ec6f57",
      "amount": 1,
      "type": "income",
      "name": {
        "first": "Curry",
        "last": "Conley"
      },
      "company": "BICOL",
      "email": "curry.conley@bicol.com",
      "phone": "+1 (946) 450-3173",
      "address": "682 Lawrence Avenue, Gilgo, Massachusetts, 4292"
    },
    {
      "_id": "5d99beb60457512fe012d3c8",
      "amount": 3,
      "type": "income",
      "name": {
        "first": "Rhoda",
        "last": "Pickett"
      },
      "company": "PYRAMAX",
      "email": "rhoda.pickett@pyramax.io",
      "phone": "+1 (938) 546-2133",
      "address": "547 Ebony Court, Rivera, Minnesota, 915"
    }
  ]
}
